LICENSE
MANIFEST.in
README.md
setup.py
wetrunner/__init__.py
wetrunner/adm.py
wetrunner/classes.py
wetrunner/definitions.py
wetrunner/parameters.py
wetrunner/rge.py
wetrunner/test_wetrunner.py
wetrunner.egg-info/PKG-INFO
wetrunner.egg-info/SOURCES.txt
wetrunner.egg-info/dependency_links.txt
wetrunner.egg-info/requires.txt
wetrunner.egg-info/top_level.txt
wetrunner/tests/data/evmat_e_old.npz
wetrunner/tests/data/evmat_s_old.npz
wetrunner/tests/data/flavio_wc_random_150.json
wetrunner/tests/data/flavio_wc_random_5.json