Metadata-Version: 1.0
Name: wetrunner
Version: 0.2
Summary: A Python package for the renormalization group evolution in the Weak Effective Theory (WET).
Home-page: https://github.com/DsixTools/python-wetrunner
Author: Jason Aebischer, Xuanyou Pan, David M. Straub
Author-email: jason.aebischer@tum.de, xuanyou.pan@tum.de, david.straub@tum.de
License: MIT
Platform: UNKNOWN
